datasette_unsafe_actor_debug/__init__.py
datasette_unsafe_actor_debug/templates/unsafe_actor.html
datasette_unsafe_actor_debug-0.2.dist-info/LICENSE
datasette_unsafe_actor_debug-0.2.dist-info/METADATA
datasette_unsafe_actor_debug-0.2.dist-info/WHEEL
datasette_unsafe_actor_debug-0.2.dist-info/entry_points.txt
datasette_unsafe_actor_debug-0.2.dist-info/top_level.txt
datasette_unsafe_actor_debug-0.2.dist-info/RECORD
