Metadata-Version: 2.1
Name: datasette-unsafe-actor-debug
Version: 0.2
Summary: Debug plugin that lets you imitate any actor
Author: Simon Willison
License: Apache-2.0
Project-URL: Homepage, https://github.com/datasette/datasette-unsafe-actor-debug
Project-URL: Changelog, https://github.com/datasette/datasette-unsafe-actor-debug/releases
Project-URL: Issues, https://github.com/datasette/datasette-unsafe-actor-debug/issues
Project-URL: CI, https://github.com/datasette/datasette-unsafe-actor-debug/actions
Classifier: Framework :: Datasette
Classifier: License :: OSI Approved :: Apache Software License
Requires-Python: >=3.8
License-File: LICENSE
Requires-Dist: datasette
Provides-Extra: test
Requires-Dist: pytest ; extra == 'test'
Requires-Dist: pytest-asyncio ; extra == 'test'
Requires-Dist: datasette-test ; extra == 'test'
